autohack/__init__.py
autohack/__main__.py
autohack/scripts.py
autohack/core/checker.py
autohack/core/constant.py
autohack/core/exception.py
autohack/core/path.py
autohack/core/run.py
autohack/core/util.py
autohack/lib/config.py
autohack/lib/i18n.py
autohack/lib/logger.py
autohack_next-1.0.11.dist-info/licenses/COPYING
autohack_next-1.0.11.dist-info/METADATA
autohack_next-1.0.11.dist-info/WHEEL
autohack_next-1.0.11.dist-info/entry_points.txt
autohack_next-1.0.11.dist-info/top_level.txt
autohack_next-1.0.11.dist-info/RECORD
