Metadata-Version: 2.4
Name: autohack-next
Version: 1.0.11
Summary:  highly customizable competitive programming Hack tool written in Python.
Author-email: gi-b716 <sganyunchi@163.com>
License:                     GNU GENERAL PUBLIC LICENSE
Project-URL: Homepage, https://github.com/gi-b716/autohack-next
Project-URL: Documentation, https://github.com/gi-b716/autohack-next/blob/main/README.md
Project-URL: Repository, https://github.com/gi-b716/autohack-next.git
Project-URL: Bug Tracker, https://github.com/gi-b716/autohack-next/issues
Keywords: competitive-programming,hack,automation
Classifier: License :: OSI Approved :: GNU General Public License v3 (GPLv3)
Classifier: Operating System :: OS Independent
Classifier: Programming Language :: Python :: 3
Classifier: Programming Language :: Python :: 3.13
Classifier: Topic :: Utilities
Requires-Python: >=3.9
License-File: COPYING
Requires-Dist: colorama>=0.4.6
Requires-Dist: platformdirs>=4.3.8
Requires-Dist: psutil>=7.0.0
Provides-Extra: build
Requires-Dist: build>=1.3.0; extra == "build"
Requires-Dist: nuitka>=2.7.12; extra == "build"
Requires-Dist: twine>=6.1.0; extra == "build"
Dynamic: license-file
